StarCC/Dicts.py
StarCC/__init__.py
StarCC/dict/CNTradPhrases.txt
StarCC/dict/CNTradRevPhrases.txt
StarCC/dict/CNTradVariants.txt
StarCC/dict/CNTradVariantsRev.txt
StarCC/dict/HKVariants.txt
StarCC/dict/HKVariantsRev.txt
StarCC/dict/HKVariantsRevPhrases.txt
StarCC/dict/JPShinjitaiCharacters.txt
StarCC/dict/JPShinjitaiPhrases.txt
StarCC/dict/JPVariants.txt
StarCC/dict/JPVariantsRev.txt
StarCC/dict/LICENSE
StarCC/dict/README.md
StarCC/dict/STCharacters.txt
StarCC/dict/STPhrases.txt
StarCC/dict/TSCharacters.txt
StarCC/dict/TSPhrases.txt
StarCC/dict/TWPhrasesIT.txt
StarCC/dict/TWPhrasesName.txt
StarCC/dict/TWPhrasesOther.txt
StarCC/dict/TWPhrasesRev.txt
StarCC/dict/TWVariants.txt
StarCC/dict/TWVariantsRev.txt
StarCC/dict/TWVariantsRevPhrases.txt
starcc-0.0.5.dist-info/LICENSE
starcc-0.0.5.dist-info/METADATA
starcc-0.0.5.dist-info/WHEEL
starcc-0.0.5.dist-info/top_level.txt
starcc-0.0.5.dist-info/RECORD
