Metadata-Version: 2.1
Name: starcc
Version: 0.0.5
Summary: Python implementation of StarCC
Home-page: https://github.com/StarCC0/starcc-py
Author: StarCC
Author-email: starcc@mail.shn.hk
License: UNKNOWN
Project-URL: Bug Reports, https://github.com/StarCC0/StarCC/issues
Project-URL: Source, https://github.com/StarCC0/StarCC
Keywords: chinese nlp natural-language-processing
Platform: UNKNOWN
Classifier: Development Status :: 4 - Beta
Classifier: Intended Audience :: Developers
Classifier: Topic :: Software Development :: Libraries :: Python Modules
Classifier: Topic :: Text Processing :: Linguistic
Classifier: Natural Language :: Chinese (Simplified)
Classifier: Natural Language :: Chinese (Traditional)
Classifier: Programming Language :: Python :: 3
Classifier: Programming Language :: Python :: 3.7
Classifier: Programming Language :: Python :: 3.8
Classifier: Programming Language :: Python :: 3.9
Classifier: Programming Language :: Python :: 3.10
Requires-Python: >=3.7, <4
Requires-Dist: jieba
Requires-Dist: pygtrie
